cocapiwrapper/__init__.py
cocapiwrapper/apiGetter.py
cocapiwrapper/apiPost.py
cocapiwrapper/application.py
cocapiwrapper/clan.py
cocapiwrapper/clanService.py
cocapiwrapper/distantSourceObject.py
cocapiwrapper/player.py
cocapiwrapper/playerService.py
cocapiwrapper/requestsSettings.py
cocapiwrapper/utils.py
cocapiwrapper-0.0.6.dist-info/LICENSE
cocapiwrapper-0.0.6.dist-info/METADATA
cocapiwrapper-0.0.6.dist-info/WHEEL
cocapiwrapper-0.0.6.dist-info/top_level.txt
cocapiwrapper-0.0.6.dist-info/RECORD
