Metadata-Version: 2.1
Name: cocapiwrapper
Version: 0.0.6
Summary: Clash of Clans API wrapper
Author: PyGIne (Ronan.T)
Author-email: <ronan.tremoureux@gmail.com>
Keywords: clashofclans,api,wrapper
Classifier: Development Status :: 1 - Planning
Classifier: Intended Audience :: Developers
Classifier: Programming Language :: Python :: 3
Classifier: Operating System :: Unix
Classifier: Operating System :: MacOS :: MacOS X
Classifier: Operating System :: Microsoft :: Windows
License-File: LICENSE
Requires-Dist: requests
Requires-Dist: python-dotenv
